xiaoweiahfang/__init__.py
xiaoweiahfang-0.0.5.dist-info/LICENSE
xiaoweiahfang-0.0.5.dist-info/METADATA
xiaoweiahfang-0.0.5.dist-info/WHEEL
xiaoweiahfang-0.0.5.dist-info/top_level.txt
xiaoweiahfang-0.0.5.dist-info/RECORD
