Metadata-Version: 2.1
Name: xiaoweiahfang
Version: 0.0.5
Summary: I am Xiao Wei or Ah Fang
Home-page: https://google.com
Author: Example Author
Author-email: tpython111@gmail.com
License: UNKNOWN
Project-URL: Bug Tracker, https://google.com
Platform: UNKNOWN
Classifier: Programming Language :: Python :: 3
Classifier: License :: OSI Approved :: MIT License
Classifier: Operating System :: OS Independent
Requires-Python: >=3.6
License-File: LICENSE
